finmodels/__init__.py
finmodels/dcf.py
finmodels/ipo.py
finmodels/lbo.py
finmodels/portfolio_optimization.py
finmodels/tests.py
finmodels-2.0.4.dist-info/METADATA
finmodels-2.0.4.dist-info/WHEEL
finmodels-2.0.4.dist-info/top_level.txt
finmodels-2.0.4.dist-info/RECORD
