Metadata-Version: 2.1
Name: finmodels
Version: 2.0.4
Summary: finmodels is a Python package that provides various financial models for analysis and optimization.
Home-page: https://github.com/arjunlimat/finmodels
Author: Tamilselvan_Arjunan
Author-email: nishantamil@gmail.com
Classifier: Programming Language :: Python :: 3
Classifier: License :: OSI Approved :: MIT License
Classifier: Operating System :: OS Independent
